jiwon_check_os_ver-0.2.0.dist-info/METADATA
jiwon_check_os_ver-0.2.0.dist-info/WHEEL
jiwon_check_os_ver-0.2.0.dist-info/entry_points.txt
jiwon_check_os_ver/__init__.py
jiwon_check_os_ver/hi.py
jiwon_check_os_ver-0.2.0.dist-info/RECORD
