Metadata-Version: 2.1
Name: jiwon-check-os-ver
Version: 0.2.0
Summary: Default template for PDM package
Author-Email: "<jiwon1118>" <<b23386585@gmail.com>>
License: MIT
Project-URL: Homepage, https://github.com/jiwon1118/jiwon-check-os-ver
Project-URL: Issues, https://github.com/jiwon1118/jiwon-check-os-ver/issues
Requires-Python: >=3.10
